{
  "legislative_session": "109",
  "identifier": "LB937",
  "title": "Adopt the Prior Learning Act and the K-12 Education Cybersecurity Act and change provisions relating to student transfers, school absences, option enrollment, extracurricular activities, reports, school employment, the improvement grant program, monitoring or providing instruction, deadlines, the Nebraska Teacher Apprenticeship Program, the Nebraska Teacher Recruitment and Retention Act, and the College Pathway Program Act",
  "from_organization": "~{\"classification\": \"legislature\"}",
  "classification": [
    "bill"
  ],
  "subject": [],
  "abstracts": [],
  "other_titles": [],
  "other_identifiers": [
    {
      "identifier": "ocd-bill-ne-109-lb937"
    }
  ],
  "actions": [
    {
      "description": "Provisions/portions of LB1243 amended into LB937 by AM2454",
      "date": "2026-04-17",
      "organization_id": "~{\"classification\": \"legislature\"}",
      "classification": [],
      "related_entities": [],
      "_processing": {
        "log_file_created": "2026-07-14T13:00:27Z"
      }
    },
    {
      "description": "Provisions/portions of LB1241 amended into LB937 by AM2454",
      "date": "2026-04-17",
      "organization_id": "~{\"classification\": \"legislature\"}",
      "classification": [],
      "related_entities": [],
      "_processing": {
        "log_file_created": "2026-07-14T13:00:27Z"
      }
    },
    {
      "description": "Provisions/portions of LB1224 amended into LB937 by AM2454",
      "date": "2026-04-17",
      "organization_id": "~{\"classification\": \"legislature\"}",
      "classification": [],
      "related_entities": [],
      "_processing": {
        "log_file_created": "2026-07-14T13:00:27Z"
      }
    },
    {
      "description": "Provisions/portions of LB1164 amended into LB937 by AM2454",
      "date": "2026-04-17",
      "organization_id": "~{\"classification\": \"legislature\"}",
      "classification": [],
      "related_entities": [],
      "_processing": {
        "log_file_created": "2026-07-14T13:00:27Z"
      }
    },
    {
      "description": "Provisions/portions of LB1146 amended into LB937 by AM2454",
      "date": "2026-04-17",
      "organization_id": "~{\"classification\": \"legislature\"}",
      "classification": [],
      "related_entities": [],
      "_processing": {
        "log_file_created": "2026-07-14T13:00:27Z"
      }
    },
    {
      "description": "Provisions/portions of LB599 amended into LB937 by AM2767",
      "date": "2026-04-17",
      "organization_id": "~{\"classification\": \"legislature\"}",
      "classification": [],
      "related_entities": [],
      "_processing": {
        "log_file_created": "2026-07-14T13:00:27Z"
      }
    },
    {
      "description": "Provisions/portions of LB417 amended into LB937 by AM2454",
      "date": "2026-04-17",
      "organization_id": "~{\"classification\": \"legislature\"}",
      "classification": [],
      "related_entities": [],
      "_processing": {
        "log_file_created": "2026-07-14T13:00:27Z"
      }
    },
    {
      "description": "Approved by Governor on April 16, 2026",
      "date": "2026-04-17",
      "organization_id": "~{\"classification\": \"executive\"}",
      "classification": [
        "executive-signature"
      ],
      "related_entities": [],
      "_processing": {
        "log_file_created": "2026-07-14T13:00:27Z"
      }
    },
    {
      "description": "Presented to Governor on  April 10, 2026",
      "date": "2026-04-17",
      "organization_id": "~{\"classification\": \"executive\"}",
      "classification": [
        "executive-receipt"
      ],
      "related_entities": [],
      "_processing": {
        "log_file_created": "2026-07-14T13:00:27Z"
      }
    },
    {
      "description": "President/Speaker signed",
      "date": "2026-04-10",
      "organization_id": "~{\"classification\": \"legislature\"}",
      "classification": [
        "passage"
      ],
      "related_entities": [],
      "_processing": {
        "log_file_created": "2026-07-14T13:00:27Z"
      }
    },
    {
      "description": "Passed on Final Reading 49-0-0",
      "date": "2026-04-10",
      "organization_id": "~{\"classification\": \"legislature\"}",
      "classification": [
        "passage"
      ],
      "related_entities": [],
      "_processing": {
        "log_file_created": "2026-07-14T13:00:27Z"
      }
    },
    {
      "description": "Dispensing of reading at large approved",
      "date": "2026-04-10",
      "organization_id": "~{\"classification\": \"legislature\"}",
      "classification": [],
      "related_entities": [],
      "_processing": {
        "log_file_created": "2026-07-14T13:00:27Z"
      }
    },
    {
      "description": "Conrad FA1006 withdrawn",
      "date": "2026-04-10",
      "organization_id": "~{\"classification\": \"legislature\"}",
      "classification": [],
      "related_entities": [],
      "_processing": {
        "log_file_created": "2026-07-14T13:00:27Z"
      }
    },
    {
      "description": "Conrad FA1005 withdrawn",
      "date": "2026-04-10",
      "organization_id": "~{\"classification\": \"legislature\"}",
      "classification": [],
      "related_entities": [],
      "_processing": {
        "log_file_created": "2026-07-14T13:00:27Z"
      }
    },
    {
      "description": "Conrad MO441 withdrawn",
      "date": "2026-04-10",
      "organization_id": "~{\"classification\": \"legislature\"}",
      "classification": [],
      "related_entities": [],
      "_processing": {
        "log_file_created": "2026-07-14T13:00:27Z"
      }
    },
    {
      "description": "Enrollment and Review ST92 recorded",
      "date": "2026-04-08",
      "organization_id": "~{\"classification\": \"legislature\"}",
      "classification": [],
      "related_entities": [],
      "_processing": {
        "log_file_created": "2026-07-14T13:00:27Z"
      }
    },
    {
      "description": "Enrollment and Review ST92 filed",
      "date": "2026-04-08",
      "organization_id": "~{\"classification\": \"legislature\"}",
      "classification": [
        "filing"
      ],
      "related_entities": [],
      "_processing": {
        "log_file_created": "2026-07-14T13:00:27Z"
      }
    },
    {
      "description": "Placed on Final Reading with ST92",
      "date": "2026-04-08",
      "organization_id": "~{\"classification\": \"legislature\"}",
      "classification": [
        "reading-3"
      ],
      "related_entities": [],
      "_processing": {
        "log_file_created": "2026-07-14T13:00:27Z"
      }
    },
    {
      "description": "Advanced to Enrollment and Review for Engrossment",
      "date": "2026-04-07",
      "organization_id": "~{\"classification\": \"legislature\"}",
      "classification": [],
      "related_entities": [],
      "_processing": {
        "log_file_created": "2026-07-14T13:00:27Z"
      }
    },
    {
      "description": "Hunt AM3118 withdrawn",
      "date": "2026-04-07",
      "organization_id": "~{\"classification\": \"legislature\"}",
      "classification": [],
      "related_entities": [],
      "_processing": {
        "log_file_created": "2026-07-14T13:00:27Z"
      }
    },
    {
      "description": "Hunt AM3118 filed",
      "date": "2026-04-07",
      "organization_id": "~{\"classification\": \"legislature\"}",
      "classification": [
        "filing"
      ],
      "related_entities": [],
      "_processing": {
        "log_file_created": "2026-07-14T13:00:27Z"
      }
    },
    {
      "description": "Kauth AM3123 adopted",
      "date": "2026-04-07",
      "organization_id": "~{\"classification\": \"legislature\"}",
      "classification": [],
      "related_entities": [],
      "_processing": {
        "log_file_created": "2026-07-14T13:00:27Z"
      }
    },
    {
      "description": "Kauth AM3123 filed",
      "date": "2026-04-07",
      "organization_id": "~{\"classification\": \"legislature\"}",
      "classification": [
        "filing"
      ],
      "related_entities": [],
      "_processing": {
        "log_file_created": "2026-07-14T13:00:27Z"
      }
    },
    {
      "description": "Rountree AM2965 lost",
      "date": "2026-04-07",
      "organization_id": "~{\"classification\": \"legislature\"}",
      "classification": [],
      "related_entities": [],
      "_processing": {
        "log_file_created": "2026-07-14T13:00:27Z"
      }
    },
    {
      "description": "Rountree AM2965 pending",
      "date": "2026-04-07",
      "organization_id": "~{\"classification\": \"legislature\"}",
      "classification": [],
      "related_entities": [],
      "_processing": {
        "log_file_created": "2026-07-14T13:00:27Z"
      }
    },
    {
      "description": "Murman AM2916 withdrawn",
      "date": "2026-04-07",
      "organization_id": "~{\"classification\": \"legislature\"}",
      "classification": [],
      "related_entities": [],
      "_processing": {
        "log_file_created": "2026-07-14T13:00:27Z"
      }
    },
    {
      "description": "Kauth AM2798 withdrawn",
      "date": "2026-04-07",
      "organization_id": "~{\"classification\": \"legislature\"}",
      "classification": [],
      "related_entities": [],
      "_processing": {
        "log_file_created": "2026-07-14T13:00:27Z"
      }
    },
    {
      "description": "Hunt AM2606 lost",
      "date": "2026-04-07",
      "organization_id": "~{\"classification\": \"legislature\"}",
      "classification": [],
      "related_entities": [],
      "_processing": {
        "log_file_created": "2026-07-14T13:00:27Z"
      }
    },
    {
      "description": "Conrad AM2668 withdrawn",
      "date": "2026-04-07",
      "organization_id": "~{\"classification\": \"legislature\"}",
      "classification": [],
      "related_entities": [],
      "_processing": {
        "log_file_created": "2026-07-14T13:00:27Z"
      }
    },
    {
      "description": "Conrad MO440 withdrawn",
      "date": "2026-04-07",
      "organization_id": "~{\"classification\": \"legislature\"}",
      "classification": [],
      "related_entities": [],
      "_processing": {
        "log_file_created": "2026-07-14T13:00:27Z"
      }
    },
    {
      "description": "DeBoer AM2767 adopted",
      "date": "2026-04-07",
      "organization_id": "~{\"classification\": \"legislature\"}",
      "classification": [],
      "related_entities": [],
      "_processing": {
        "log_file_created": "2026-07-14T13:00:27Z"
      }
    },
    {
      "description": "Conrad FA1004 withdrawn",
      "date": "2026-04-07",
      "organization_id": "~{\"classification\": \"legislature\"}",
      "classification": [],
      "related_entities": [],
      "_processing": {
        "log_file_created": "2026-07-14T13:00:27Z"
      }
    },
    {
      "description": "Conrad FA1003 withdrawn",
      "date": "2026-04-07",
      "organization_id": "~{\"classification\": \"legislature\"}",
      "classification": [],
      "related_entities": [],
      "_processing": {
        "log_file_created": "2026-07-14T13:00:27Z"
      }
    },
    {
      "description": "Murman FA558 withdrawn",
      "date": "2026-04-07",
      "organization_id": "~{\"classification\": \"legislature\"}",
      "classification": [],
      "related_entities": [],
      "_processing": {
        "log_file_created": "2026-07-14T13:00:27Z"
      }
    },
    {
      "description": "Kauth FA1180 adopted",
      "date": "2026-04-07",
      "organization_id": "~{\"classification\": \"legislature\"}",
      "classification": [],
      "related_entities": [],
      "_processing": {
        "log_file_created": "2026-07-14T13:00:27Z"
      }
    },
    {
      "description": "Kauth FA1180 to AM3084 filed",
      "date": "2026-04-07",
      "organization_id": "~{\"classification\": \"legislature\"}",
      "classification": [
        "filing"
      ],
      "related_entities": [],
      "_processing": {
        "log_file_created": "2026-07-14T13:00:27Z"
      }
    },
    {
      "description": "Lonowski FA1177 adopted",
      "date": "2026-04-07",
      "organization_id": "~{\"classification\": \"legislature\"}",
      "classification": [],
      "related_entities": [],
      "_processing": {
        "log_file_created": "2026-07-14T13:00:27Z"
      }
    },
    {
      "description": "Lonowski FA1177 to AM3084 filed",
      "date": "2026-04-07",
      "organization_id": "~{\"classification\": \"legislature\"}",
      "classification": [
        "filing"
      ],
      "related_entities": [],
      "_processing": {
        "log_file_created": "2026-07-14T13:00:27Z"
      }
    },
    {
      "description": "Murman AM3084 adopted",
      "date": "2026-04-07",
      "organization_id": "~{\"classification\": \"legislature\"}",
      "classification": [],
      "related_entities": [],
      "_processing": {
        "log_file_created": "2026-07-14T13:00:27Z"
      }
    },
    {
      "description": "Murman FA556 withdrawn",
      "date": "2026-04-07",
      "organization_id": "~{\"classification\": \"legislature\"}",
      "classification": [],
      "related_entities": [],
      "_processing": {
        "log_file_created": "2026-07-14T13:00:27Z"
      }
    },
    {
      "description": "No objections to unanimous consent request to withdraw and substitute amendment",
      "date": "2026-04-07",
      "organization_id": "~{\"classification\": \"legislature\"}",
      "classification": [],
      "related_entities": [],
      "_processing": {
        "log_file_created": "2026-07-14T13:00:27Z"
      }
    },
    {
      "description": "Murman AM3084 filed",
      "date": "2026-04-07",
      "organization_id": "~{\"classification\": \"legislature\"}",
      "classification": [
        "filing"
      ],
      "related_entities": [],
      "_processing": {
        "log_file_created": "2026-07-14T13:00:27Z"
      }
    },
    {
      "description": "Kauth FA554 withdrawn",
      "date": "2026-04-07",
      "organization_id": "~{\"classification\": \"legislature\"}",
      "classification": [],
      "related_entities": [],
      "_processing": {
        "log_file_created": "2026-07-14T13:00:27Z"
      }
    },
    {
      "description": "Conrad MO439 withdrawn",
      "date": "2026-04-07",
      "organization_id": "~{\"classification\": \"legislature\"}",
      "classification": [],
      "related_entities": [],
      "_processing": {
        "log_file_created": "2026-07-14T13:00:27Z"
      }
    },
    {
      "description": "Conrad MO438 withdrawn",
      "date": "2026-04-07",
      "organization_id": "~{\"classification\": \"legislature\"}",
      "classification": [],
      "related_entities": [],
      "_processing": {
        "log_file_created": "2026-07-14T13:00:27Z"
      }
    },
    {
      "description": "Enrollment and Review ER155 adopted",
      "date": "2026-04-07",
      "organization_id": "~{\"classification\": \"legislature\"}",
      "classification": [],
      "related_entities": [],
      "_processing": {
        "log_file_created": "2026-07-14T13:00:27Z"
      }
    },
    {
      "description": "Rountree AM2965 filed",
      "date": "2026-03-31",
      "organization_id": "~{\"classification\": \"legislature\"}",
      "classification": [
        "filing"
      ],
      "related_entities": [],
      "_processing": {
        "log_file_created": "2026-07-14T13:00:27Z"
      }
    },
    {
      "description": "Murman AM2916 filed",
      "date": "2026-03-30",
      "organization_id": "~{\"classification\": \"legislature\"}",
      "classification": [
        "filing"
      ],
      "related_entities": [],
      "_processing": {
        "log_file_created": "2026-07-14T13:00:27Z"
      }
    },
    {
      "description": "Kauth AM2798 filed",
      "date": "2026-03-30",
      "organization_id": "~{\"classification\": \"legislature\"}",
      "classification": [
        "filing"
      ],
      "related_entities": [],
      "_processing": {
        "log_file_created": "2026-07-14T13:00:27Z"
      }
    },
    {
      "description": "Enrollment and Review ER155 filed",
      "date": "2026-03-25",
      "organization_id": "~{\"classification\": \"legislature\"}",
      "classification": [
        "filing"
      ],
      "related_entities": [],
      "_processing": {
        "log_file_created": "2026-07-14T13:00:27Z"
      }
    },
    {
      "description": "Placed on Select File with ER155",
      "date": "2026-03-25",
      "organization_id": "~{\"classification\": \"legislature\"}",
      "classification": [
        "filing"
      ],
      "related_entities": [],
      "_processing": {
        "log_file_created": "2026-07-14T13:00:27Z"
      }
    },
    {
      "description": "Hunt AM2606 filed",
      "date": "2026-03-25",
      "organization_id": "~{\"classification\": \"legislature\"}",
      "classification": [
        "filing"
      ],
      "related_entities": [],
      "_processing": {
        "log_file_created": "2026-07-14T13:00:27Z"
      }
    },
    {
      "description": "Conrad AM2668 filed",
      "date": "2026-03-20",
      "organization_id": "~{\"classification\": \"legislature\"}",
      "classification": [
        "filing"
      ],
      "related_entities": [],
      "_processing": {
        "log_file_created": "2026-07-14T13:00:27Z"
      }
    },
    {
      "description": "DeBoer AM2767 filed",
      "date": "2026-03-20",
      "organization_id": "~{\"classification\": \"legislature\"}",
      "classification": [
        "filing"
      ],
      "related_entities": [],
      "_processing": {
        "log_file_created": "2026-07-14T13:00:27Z"
      }
    },
    {
      "description": "Advanced to Enrollment and Review Initial",
      "date": "2026-03-17",
      "organization_id": "~{\"classification\": \"legislature\"}",
      "classification": [],
      "related_entities": [],
      "_processing": {
        "log_file_created": "2026-07-14T13:00:27Z"
      }
    },
    {
      "description": "Conrad FA1002 withdrawn",
      "date": "2026-03-17",
      "organization_id": "~{\"classification\": \"legislature\"}",
      "classification": [],
      "related_entities": [],
      "_processing": {
        "log_file_created": "2026-07-14T13:00:27Z"
      }
    },
    {
      "description": "Conrad FA1001 withdrawn",
      "date": "2026-03-17",
      "organization_id": "~{\"classification\": \"legislature\"}",
      "classification": [],
      "related_entities": [],
      "_processing": {
        "log_file_created": "2026-07-14T13:00:27Z"
      }
    },
    {
      "description": "Murman FA557 withdrawn",
      "date": "2026-03-17",
      "organization_id": "~{\"classification\": \"legislature\"}",
      "classification": [],
      "related_entities": [],
      "_processing": {
        "log_file_created": "2026-07-14T13:00:27Z"
      }
    },
    {
      "description": "Murman FA555 withdrawn",
      "date": "2026-03-17",
      "organization_id": "~{\"classification\": \"legislature\"}",
      "classification": [],
      "related_entities": [],
      "_processing": {
        "log_file_created": "2026-07-14T13:00:27Z"
      }
    },
    {
      "description": "Education AM2454 adopted",
      "date": "2026-03-17",
      "organization_id": "~{\"classification\": \"legislature\"}",
      "classification": [],
      "related_entities": [],
      "_processing": {
        "log_file_created": "2026-07-14T13:00:27Z"
      }
    },
    {
      "description": "Conrad MO437 withdrawn",
      "date": "2026-03-17",
      "organization_id": "~{\"classification\": \"legislature\"}",
      "classification": [],
      "related_entities": [],
      "_processing": {
        "log_file_created": "2026-07-14T13:00:27Z"
      }
    },
    {
      "description": "Conrad MO436 withdrawn",
      "date": "2026-03-17",
      "organization_id": "~{\"classification\": \"legislature\"}",
      "classification": [],
      "related_entities": [],
      "_processing": {
        "log_file_created": "2026-07-14T13:00:27Z"
      }
    },
    {
      "description": "Conrad MO435 withdrawn",
      "date": "2026-03-17",
      "organization_id": "~{\"classification\": \"legislature\"}",
      "classification": [],
      "related_entities": [],
      "_processing": {
        "log_file_created": "2026-07-14T13:00:27Z"
      }
    },
    {
      "description": "Education AM2454 filed",
      "date": "2026-03-10",
      "organization_id": "~{\"classification\": \"legislature\"}",
      "classification": [
        "filing"
      ],
      "related_entities": [],
      "_processing": {
        "log_file_created": "2026-07-14T13:00:27Z"
      }
    },
    {
      "description": "Placed on General File with AM2454",
      "date": "2026-03-10",
      "organization_id": "~{\"classification\": \"legislature\"}",
      "classification": [
        "committee-passage"
      ],
      "related_entities": [],
      "_processing": {
        "log_file_created": "2026-07-14T13:00:27Z"
      }
    },
    {
      "description": "Conrad MO441 Recommit to the Education Committee filed",
      "date": "2026-02-20",
      "organization_id": "~{\"classification\": \"legislature\"}",
      "classification": [
        "filing"
      ],
      "related_entities": [],
      "_processing": {
        "log_file_created": "2026-07-14T13:00:27Z"
      }
    },
    {
      "description": "Conrad MO440 Indefinitely postpone filed",
      "date": "2026-02-20",
      "organization_id": "~{\"classification\": \"legislature\"}",
      "classification": [
        "filing"
      ],
      "related_entities": [],
      "_processing": {
        "log_file_created": "2026-07-14T13:00:27Z"
      }
    },
    {
      "description": "Conrad MO439 Recommit to the Education Committee filed",
      "date": "2026-02-20",
      "organization_id": "~{\"classification\": \"legislature\"}",
      "classification": [
        "filing"
      ],
      "related_entities": [],
      "_processing": {
        "log_file_created": "2026-07-14T13:00:27Z"
      }
    },
    {
      "description": "Conrad MO438 Bracket until April 17, 2026 filed",
      "date": "2026-02-20",
      "organization_id": "~{\"classification\": \"legislature\"}",
      "classification": [
        "filing"
      ],
      "related_entities": [],
      "_processing": {
        "log_file_created": "2026-07-14T13:00:27Z"
      }
    },
    {
      "description": "Conrad MO437 Recommit to the Education Committee filed",
      "date": "2026-02-20",
      "organization_id": "~{\"classification\": \"legislature\"}",
      "classification": [
        "filing"
      ],
      "related_entities": [],
      "_processing": {
        "log_file_created": "2026-07-14T13:00:27Z"
      }
    },
    {
      "description": "Conrad MO436 Bracket until April 17, 2026 filed",
      "date": "2026-02-20",
      "organization_id": "~{\"classification\": \"legislature\"}",
      "classification": [
        "filing"
      ],
      "related_entities": [],
      "_processing": {
        "log_file_created": "2026-07-14T13:00:27Z"
      }
    },
    {
      "description": "Conrad MO435 Indefinitely postpone pursuant to Rule 6, Sec. 3(f) filed",
      "date": "2026-02-20",
      "organization_id": "~{\"classification\": \"legislature\"}",
      "classification": [
        "filing"
      ],
      "related_entities": [],
      "_processing": {
        "log_file_created": "2026-07-14T13:00:27Z"
      }
    },
    {
      "description": "Conrad FA1006 filed",
      "date": "2026-02-20",
      "organization_id": "~{\"classification\": \"legislature\"}",
      "classification": [
        "filing"
      ],
      "related_entities": [],
      "_processing": {
        "log_file_created": "2026-07-14T13:00:27Z"
      }
    },
    {
      "description": "Conrad FA1005 filed",
      "date": "2026-02-20",
      "organization_id": "~{\"classification\": \"legislature\"}",
      "classification": [
        "filing"
      ],
      "related_entities": [],
      "_processing": {
        "log_file_created": "2026-07-14T13:00:27Z"
      }
    },
    {
      "description": "Conrad FA1004 filed",
      "date": "2026-02-20",
      "organization_id": "~{\"classification\": \"legislature\"}",
      "classification": [
        "filing"
      ],
      "related_entities": [],
      "_processing": {
        "log_file_created": "2026-07-14T13:00:27Z"
      }
    },
    {
      "description": "Conrad FA1003 filed",
      "date": "2026-02-20",
      "organization_id": "~{\"classification\": \"legislature\"}",
      "classification": [
        "filing"
      ],
      "related_entities": [],
      "_processing": {
        "log_file_created": "2026-07-14T13:00:27Z"
      }
    },
    {
      "description": "Conrad FA1002 filed",
      "date": "2026-02-20",
      "organization_id": "~{\"classification\": \"legislature\"}",
      "classification": [
        "filing"
      ],
      "related_entities": [],
      "_processing": {
        "log_file_created": "2026-07-14T13:00:27Z"
      }
    },
    {
      "description": "Conrad FA1001 filed",
      "date": "2026-02-20",
      "organization_id": "~{\"classification\": \"legislature\"}",
      "classification": [
        "filing"
      ],
      "related_entities": [],
      "_processing": {
        "log_file_created": "2026-07-14T13:00:27Z"
      }
    },
    {
      "description": "Education priority bill",
      "date": "2026-02-19",
      "organization_id": "~{\"classification\": \"legislature\"}",
      "classification": [],
      "related_entities": [],
      "_processing": {
        "log_file_created": "2026-07-14T13:00:27Z"
      }
    },
    {
      "description": "Notice of hearing for January 20, 2026",
      "date": "2026-01-13",
      "organization_id": "~{\"classification\": \"legislature\"}",
      "classification": [],
      "related_entities": [],
      "_processing": {
        "log_file_created": "2026-07-14T13:00:27Z"
      }
    },
    {
      "description": "Referred to Education Committee",
      "date": "2026-01-13",
      "organization_id": "~{\"classification\": \"legislature\"}",
      "classification": [
        "referral-committee"
      ],
      "related_entities": [],
      "_processing": {
        "log_file_created": "2026-07-14T13:00:27Z"
      }
    },
    {
      "description": "Murman FA558 filed",
      "date": "2026-01-09",
      "organization_id": "~{\"classification\": \"legislature\"}",
      "classification": [
        "filing"
      ],
      "related_entities": [],
      "_processing": {
        "log_file_created": "2026-07-14T13:00:27Z"
      }
    },
    {
      "description": "Murman FA557 filed",
      "date": "2026-01-09",
      "organization_id": "~{\"classification\": \"legislature\"}",
      "classification": [
        "filing"
      ],
      "related_entities": [],
      "_processing": {
        "log_file_created": "2026-07-14T13:00:27Z"
      }
    },
    {
      "description": "Murman FA556 filed",
      "date": "2026-01-09",
      "organization_id": "~{\"classification\": \"legislature\"}",
      "classification": [
        "filing"
      ],
      "related_entities": [],
      "_processing": {
        "log_file_created": "2026-07-14T13:00:27Z"
      }
    },
    {
      "description": "Murman FA555 filed",
      "date": "2026-01-09",
      "organization_id": "~{\"classification\": \"legislature\"}",
      "classification": [
        "filing"
      ],
      "related_entities": [],
      "_processing": {
        "log_file_created": "2026-07-14T13:00:27Z"
      }
    },
    {
      "description": "Kauth FA554 filed",
      "date": "2026-01-09",
      "organization_id": "~{\"classification\": \"legislature\"}",
      "classification": [
        "filing"
      ],
      "related_entities": [],
      "_processing": {
        "log_file_created": "2026-07-14T13:00:27Z"
      }
    },
    {
      "description": "Date of introduction",
      "date": "2026-01-09",
      "organization_id": "~{\"classification\": \"legislature\"}",
      "classification": [
        "introduction"
      ],
      "related_entities": [],
      "_processing": {
        "log_file_created": "2026-07-14T13:00:27Z"
      }
    }
  ],
  "sponsorships": [
    {
      "name": "Education Committee",
      "classification": "primary",
      "entity_type": "organization",
      "primary": true,
      "person_id": null,
      "organization_id": "~{\"name\": \"Education Committee\"}"
    }
  ],
  "related_bills": [],
  "versions": [
    {
      "note": "Introduced",
      "links": [
        {
          "url": "https://nebraskalegislature.gov/FloorDocs/109/PDF/Intro/LB937.pdf",
          "media_type": "application/pdf"
        }
      ],
      "date": "",
      "classification": ""
    },
    {
      "note": "Final Reading",
      "links": [
        {
          "url": "https://nebraskalegislature.gov/FloorDocs/109/PDF/Final/LB937.pdf",
          "media_type": "application/pdf"
        }
      ],
      "date": "",
      "classification": ""
    },
    {
      "note": "Slip Law",
      "links": [
        {
          "url": "https://nebraskalegislature.gov/FloorDocs/109/PDF/Slip/LB937.pdf",
          "media_type": "application/pdf"
        }
      ],
      "date": "",
      "classification": ""
    },
    {
      "note": "Education AM2454",
      "links": [
        {
          "url": "https://nebraskalegislature.gov/FloorDocs/109/PDF/AM/AM2454.pdf",
          "media_type": "application/pdf"
        }
      ],
      "date": "",
      "classification": ""
    },
    {
      "note": "Enrollment and Review ER155",
      "links": [
        {
          "url": "https://nebraskalegislature.gov/FloorDocs/109/PDF/AM/ER155.pdf",
          "media_type": "application/pdf"
        }
      ],
      "date": "",
      "classification": ""
    },
    {
      "note": "Murman AM3084",
      "links": [
        {
          "url": "https://nebraskalegislature.gov/FloorDocs/109/PDF/AM/AM3084.pdf",
          "media_type": "application/pdf"
        }
      ],
      "date": "",
      "classification": ""
    },
    {
      "note": "Lonowski FA1177",
      "links": [
        {
          "url": "https://nebraskalegislature.gov/FloorDocs/109/PDF/AM/FA1177.pdf",
          "media_type": "application/pdf"
        }
      ],
      "date": "",
      "classification": ""
    },
    {
      "note": "Kauth FA1180",
      "links": [
        {
          "url": "https://nebraskalegislature.gov/FloorDocs/109/PDF/AM/FA1180.pdf",
          "media_type": "application/pdf"
        }
      ],
      "date": "",
      "classification": ""
    },
    {
      "note": "DeBoer AM2767",
      "links": [
        {
          "url": "https://nebraskalegislature.gov/FloorDocs/109/PDF/AM/AM2767.pdf",
          "media_type": "application/pdf"
        }
      ],
      "date": "",
      "classification": ""
    },
    {
      "note": "Kauth AM3123",
      "links": [
        {
          "url": "https://nebraskalegislature.gov/FloorDocs/109/PDF/AM/AM3123.pdf",
          "media_type": "application/pdf"
        }
      ],
      "date": "",
      "classification": ""
    }
  ],
  "documents": [
    {
      "note": "Statement of Intent",
      "links": [
        {
          "url": "https://nebraskalegislature.gov/FloorDocs/109/PDF/SI/LB937.pdf",
          "media_type": "application/pdf"
        }
      ],
      "date": "",
      "classification": ""
    },
    {
      "note": "Committee Statement",
      "links": [
        {
          "url": "https://nebraskalegislature.gov/FloorDocs/109/PDF/CS/LB937.pdf",
          "media_type": "application/pdf"
        }
      ],
      "date": "",
      "classification": ""
    },
    {
      "note": "Fiscal Note",
      "links": [
        {
          "url": "https://nebraskalegislature.gov/bills/view_fiscal.php?DocumentID=63153",
          "media_type": "application/pdf"
        }
      ],
      "date": "",
      "classification": ""
    },
    {
      "note": "Conrad MO436 (withdrawn)",
      "links": [
        {
          "url": "https://nebraskalegislature.gov/FloorDocs/109/PDF/AM/MO436.pdf",
          "media_type": "application/pdf"
        }
      ],
      "date": "",
      "classification": ""
    },
    {
      "note": "Conrad MO435 (withdrawn)",
      "links": [
        {
          "url": "https://nebraskalegislature.gov/FloorDocs/109/PDF/AM/MO435.pdf",
          "media_type": "application/pdf"
        }
      ],
      "date": "",
      "classification": ""
    },
    {
      "note": "Conrad FA1002 (withdrawn)",
      "links": [
        {
          "url": "https://nebraskalegislature.gov/FloorDocs/109/PDF/AM/FA1002.pdf",
          "media_type": "application/pdf"
        }
      ],
      "date": "",
      "classification": ""
    },
    {
      "note": "Conrad FA1001 (withdrawn)",
      "links": [
        {
          "url": "https://nebraskalegislature.gov/FloorDocs/109/PDF/AM/FA1001.pdf",
          "media_type": "application/pdf"
        }
      ],
      "date": "",
      "classification": ""
    },
    {
      "note": "Conrad MO437 (withdrawn)",
      "links": [
        {
          "url": "https://nebraskalegislature.gov/FloorDocs/109/PDF/AM/MO437.pdf",
          "media_type": "application/pdf"
        }
      ],
      "date": "",
      "classification": ""
    },
    {
      "note": "Murman FA555 (withdrawn)",
      "links": [
        {
          "url": "https://nebraskalegislature.gov/FloorDocs/109/PDF/AM/FA555.pdf",
          "media_type": "application/pdf"
        }
      ],
      "date": "",
      "classification": ""
    },
    {
      "note": "Murman FA557 (withdrawn)",
      "links": [
        {
          "url": "https://nebraskalegislature.gov/FloorDocs/109/PDF/AM/FA557.pdf",
          "media_type": "application/pdf"
        }
      ],
      "date": "",
      "classification": ""
    },
    {
      "note": "Conrad MO438 (withdrawn)",
      "links": [
        {
          "url": "https://nebraskalegislature.gov/FloorDocs/109/PDF/AM/MO438.pdf",
          "media_type": "application/pdf"
        }
      ],
      "date": "",
      "classification": ""
    },
    {
      "note": "Conrad MO439 (withdrawn)",
      "links": [
        {
          "url": "https://nebraskalegislature.gov/FloorDocs/109/PDF/AM/MO439.pdf",
          "media_type": "application/pdf"
        }
      ],
      "date": "",
      "classification": ""
    },
    {
      "note": "Kauth FA554 (withdrawn)",
      "links": [
        {
          "url": "https://nebraskalegislature.gov/FloorDocs/109/PDF/AM/FA554.pdf",
          "media_type": "application/pdf"
        }
      ],
      "date": "",
      "classification": ""
    },
    {
      "note": "Murman FA556 (withdrawn)",
      "links": [
        {
          "url": "https://nebraskalegislature.gov/FloorDocs/109/PDF/AM/FA556.pdf",
          "media_type": "application/pdf"
        }
      ],
      "date": "",
      "classification": ""
    },
    {
      "note": "Murman FA558 (withdrawn)",
      "links": [
        {
          "url": "https://nebraskalegislature.gov/FloorDocs/109/PDF/AM/FA558.pdf",
          "media_type": "application/pdf"
        }
      ],
      "date": "",
      "classification": ""
    },
    {
      "note": "Conrad FA1003 (withdrawn)",
      "links": [
        {
          "url": "https://nebraskalegislature.gov/FloorDocs/109/PDF/AM/FA1003.pdf",
          "media_type": "application/pdf"
        }
      ],
      "date": "",
      "classification": ""
    },
    {
      "note": "Conrad FA1004 (withdrawn)",
      "links": [
        {
          "url": "https://nebraskalegislature.gov/FloorDocs/109/PDF/AM/FA1004.pdf",
          "media_type": "application/pdf"
        }
      ],
      "date": "",
      "classification": ""
    },
    {
      "note": "Conrad AM2668 (withdrawn)",
      "links": [
        {
          "url": "https://nebraskalegislature.gov/FloorDocs/109/PDF/AM/AM2668.pdf",
          "media_type": "application/pdf"
        }
      ],
      "date": "",
      "classification": ""
    },
    {
      "note": "Hunt AM2606 (lost)",
      "links": [
        {
          "url": "https://nebraskalegislature.gov/FloorDocs/109/PDF/AM/AM2606.pdf",
          "media_type": "application/pdf"
        }
      ],
      "date": "",
      "classification": ""
    },
    {
      "note": "Kauth AM2798 (withdrawn)",
      "links": [
        {
          "url": "https://nebraskalegislature.gov/FloorDocs/109/PDF/AM/AM2798.pdf",
          "media_type": "application/pdf"
        }
      ],
      "date": "",
      "classification": ""
    },
    {
      "note": "Murman AM2916 (withdrawn)",
      "links": [
        {
          "url": "https://nebraskalegislature.gov/FloorDocs/109/PDF/AM/AM2916.pdf",
          "media_type": "application/pdf"
        }
      ],
      "date": "",
      "classification": ""
    },
    {
      "note": "Conrad MO440 (withdrawn)",
      "links": [
        {
          "url": "https://nebraskalegislature.gov/FloorDocs/109/PDF/AM/MO440.pdf",
          "media_type": "application/pdf"
        }
      ],
      "date": "",
      "classification": ""
    },
    {
      "note": "Rountree AM2965 (lost)",
      "links": [
        {
          "url": "https://nebraskalegislature.gov/FloorDocs/109/PDF/AM/AM2965.pdf",
          "media_type": "application/pdf"
        }
      ],
      "date": "",
      "classification": ""
    },
    {
      "note": "Hunt AM3118 (withdrawn)",
      "links": [
        {
          "url": "https://nebraskalegislature.gov/FloorDocs/109/PDF/AM/AM3118.pdf",
          "media_type": "application/pdf"
        }
      ],
      "date": "",
      "classification": ""
    },
    {
      "note": "Enrollment and Review ST92 (recorded)",
      "links": [
        {
          "url": "https://nebraskalegislature.gov/FloorDocs/109/PDF/AM/ST92.pdf",
          "media_type": "application/pdf"
        }
      ],
      "date": "",
      "classification": ""
    },
    {
      "note": "Conrad MO441 (withdrawn)",
      "links": [
        {
          "url": "https://nebraskalegislature.gov/FloorDocs/109/PDF/AM/MO441.pdf",
          "media_type": "application/pdf"
        }
      ],
      "date": "",
      "classification": ""
    },
    {
      "note": "Conrad FA1006 (withdrawn)",
      "links": [
        {
          "url": "https://nebraskalegislature.gov/FloorDocs/109/PDF/AM/FA1006.pdf",
          "media_type": "application/pdf"
        }
      ],
      "date": "",
      "classification": ""
    },
    {
      "note": "Conrad FA1005 (withdrawn)",
      "links": [
        {
          "url": "https://nebraskalegislature.gov/FloorDocs/109/PDF/AM/FA1005.pdf",
          "media_type": "application/pdf"
        }
      ],
      "date": "",
      "classification": ""
    }
  ],
  "citations": [],
  "sources": [
    {
      "url": "https://nebraskalegislature.gov/bills/search_by_date.php?SessionDay=2026",
      "note": ""
    },
    {
      "url": "https://nebraskalegislature.gov/bills/view_bill.php?DocumentID=63153",
      "note": ""
    }
  ],
  "extras": {
    "NE_REF_DATE": "January 20, 2026",
    "NE_REF_COM": "Education Committee",
    "NE_PRIORITIZER": "Education Committee"
  },
  "jurisdiction": {
    "id": "ocd-jurisdiction/country:us/state:ne/government",
    "name": "Nebraska",
    "classification": "state",
    "division_id": "ocd-division/country:us/state:ne"
  },
  "_processing": {
    "logs_latest_update": "2026-07-14T13:00:27Z",
    "text_extraction_latest_update": "2026-07-21T06:11:17.930627Z"
  }
}