{
  "legislative_session": "109",
  "identifier": "LB938",
  "title": "Adopt the First-Time Home Buyer Savings Account Act and provide for income tax adjustments",
  "from_organization": "~{\"classification\": \"legislature\"}",
  "classification": [
    "bill"
  ],
  "subject": [],
  "abstracts": [],
  "other_titles": [],
  "other_identifiers": [
    {
      "identifier": "ocd-bill-ne-109-lb938"
    }
  ],
  "actions": [
    {
      "description": "Provisions/portions of LB938 amended into LB803 by AM2651",
      "date": "2026-04-17",
      "organization_id": "~{\"classification\": \"legislature\"}",
      "classification": [],
      "related_entities": [],
      "_processing": {
        "log_file_created": "2026-07-14T13:00:28Z"
      }
    },
    {
      "description": "Indefinitely postponed",
      "date": "2026-04-17",
      "organization_id": "~{\"classification\": \"legislature\"}",
      "classification": [
        "committee-failure"
      ],
      "related_entities": [],
      "_processing": {
        "log_file_created": "2026-07-14T13:00:28Z"
      }
    },
    {
      "description": "Prokop name added",
      "date": "2026-03-11",
      "organization_id": "~{\"classification\": \"legislature\"}",
      "classification": [],
      "related_entities": [],
      "_processing": {
        "log_file_created": "2026-07-14T13:00:28Z"
      }
    },
    {
      "description": "Rountree name added",
      "date": "2026-03-06",
      "organization_id": "~{\"classification\": \"legislature\"}",
      "classification": [],
      "related_entities": [],
      "_processing": {
        "log_file_created": "2026-07-14T13:00:28Z"
      }
    },
    {
      "description": "Placed on General File",
      "date": "2026-02-23",
      "organization_id": "~{\"classification\": \"legislature\"}",
      "classification": [
        "committee-passage"
      ],
      "related_entities": [],
      "_processing": {
        "log_file_created": "2026-07-14T13:00:28Z"
      }
    },
    {
      "description": "Storm name added",
      "date": "2026-02-20",
      "organization_id": "~{\"classification\": \"legislature\"}",
      "classification": [],
      "related_entities": [],
      "_processing": {
        "log_file_created": "2026-07-14T13:00:28Z"
      }
    },
    {
      "description": "Storm priority bill",
      "date": "2026-02-19",
      "organization_id": "~{\"classification\": \"legislature\"}",
      "classification": [],
      "related_entities": [],
      "_processing": {
        "log_file_created": "2026-07-14T13:00:28Z"
      }
    },
    {
      "description": "Kauth name added",
      "date": "2026-02-17",
      "organization_id": "~{\"classification\": \"legislature\"}",
      "classification": [],
      "related_entities": [],
      "_processing": {
        "log_file_created": "2026-07-14T13:00:28Z"
      }
    },
    {
      "description": "Wordekemper name added",
      "date": "2026-02-09",
      "organization_id": "~{\"classification\": \"legislature\"}",
      "classification": [],
      "related_entities": [],
      "_processing": {
        "log_file_created": "2026-07-14T13:00:28Z"
      }
    },
    {
      "description": "Notice of hearing for February 12, 2026",
      "date": "2026-02-05",
      "organization_id": "~{\"classification\": \"legislature\"}",
      "classification": [],
      "related_entities": [],
      "_processing": {
        "log_file_created": "2026-07-14T13:00:28Z"
      }
    },
    {
      "description": "DeKay name added",
      "date": "2026-02-04",
      "organization_id": "~{\"classification\": \"legislature\"}",
      "classification": [],
      "related_entities": [],
      "_processing": {
        "log_file_created": "2026-07-14T13:00:28Z"
      }
    },
    {
      "description": "Murman name added",
      "date": "2026-02-03",
      "organization_id": "~{\"classification\": \"legislature\"}",
      "classification": [],
      "related_entities": [],
      "_processing": {
        "log_file_created": "2026-07-14T13:00:28Z"
      }
    },
    {
      "description": "Lippincott name added",
      "date": "2026-02-03",
      "organization_id": "~{\"classification\": \"legislature\"}",
      "classification": [],
      "related_entities": [],
      "_processing": {
        "log_file_created": "2026-07-14T13:00:28Z"
      }
    },
    {
      "description": "Andersen name added",
      "date": "2026-02-02",
      "organization_id": "~{\"classification\": \"legislature\"}",
      "classification": [],
      "related_entities": [],
      "_processing": {
        "log_file_created": "2026-07-14T13:00:28Z"
      }
    },
    {
      "description": "Hardin name added",
      "date": "2026-01-23",
      "organization_id": "~{\"classification\": \"legislature\"}",
      "classification": [],
      "related_entities": [],
      "_processing": {
        "log_file_created": "2026-07-14T13:00:28Z"
      }
    },
    {
      "description": "Cavanaugh, J. name added",
      "date": "2026-01-23",
      "organization_id": "~{\"classification\": \"legislature\"}",
      "classification": [],
      "related_entities": [],
      "_processing": {
        "log_file_created": "2026-07-14T13:00:28Z"
      }
    },
    {
      "description": "Dover name added",
      "date": "2026-01-20",
      "organization_id": "~{\"classification\": \"legislature\"}",
      "classification": [],
      "related_entities": [],
      "_processing": {
        "log_file_created": "2026-07-14T13:00:28Z"
      }
    },
    {
      "description": "Referred to Revenue Committee",
      "date": "2026-01-13",
      "organization_id": "~{\"classification\": \"legislature\"}",
      "classification": [
        "referral-committee"
      ],
      "related_entities": [],
      "_processing": {
        "log_file_created": "2026-07-14T13:00:28Z"
      }
    },
    {
      "description": "Bostar name added",
      "date": "2026-01-12",
      "organization_id": "~{\"classification\": \"legislature\"}",
      "classification": [],
      "related_entities": [],
      "_processing": {
        "log_file_created": "2026-07-14T13:00:28Z"
      }
    },
    {
      "description": "Conrad name added",
      "date": "2026-01-12",
      "organization_id": "~{\"classification\": \"legislature\"}",
      "classification": [],
      "related_entities": [],
      "_processing": {
        "log_file_created": "2026-07-14T13:00:28Z"
      }
    },
    {
      "description": "Kauth FA596 filed",
      "date": "2026-01-12",
      "organization_id": "~{\"classification\": \"legislature\"}",
      "classification": [
        "filing"
      ],
      "related_entities": [],
      "_processing": {
        "log_file_created": "2026-07-14T13:00:28Z"
      }
    },
    {
      "description": "Date of introduction",
      "date": "2026-01-09",
      "organization_id": "~{\"classification\": \"legislature\"}",
      "classification": [
        "introduction"
      ],
      "related_entities": [],
      "_processing": {
        "log_file_created": "2026-07-14T13:00:28Z"
      }
    }
  ],
  "sponsorships": [
    {
      "name": "Hallstrom",
      "classification": "primary",
      "entity_type": "person",
      "primary": true,
      "person_id": "~{\"name\": \"Hallstrom\"}",
      "organization_id": null
    },
    {
      "name": "Prokop",
      "classification": "cosponsor",
      "entity_type": "person",
      "primary": false,
      "person_id": "~{\"name\": \"Prokop\"}",
      "organization_id": null
    },
    {
      "name": "Rountree",
      "classification": "cosponsor",
      "entity_type": "person",
      "primary": false,
      "person_id": "~{\"name\": \"Rountree\"}",
      "organization_id": null
    },
    {
      "name": "Storm",
      "classification": "cosponsor",
      "entity_type": "person",
      "primary": false,
      "person_id": "~{\"name\": \"Storm\"}",
      "organization_id": null
    },
    {
      "name": "Kauth",
      "classification": "cosponsor",
      "entity_type": "person",
      "primary": false,
      "person_id": "~{\"name\": \"Kauth\"}",
      "organization_id": null
    },
    {
      "name": "Wordekemper",
      "classification": "cosponsor",
      "entity_type": "person",
      "primary": false,
      "person_id": "~{\"name\": \"Wordekemper\"}",
      "organization_id": null
    },
    {
      "name": "DeKay",
      "classification": "cosponsor",
      "entity_type": "person",
      "primary": false,
      "person_id": "~{\"name\": \"DeKay\"}",
      "organization_id": null
    },
    {
      "name": "Murman",
      "classification": "cosponsor",
      "entity_type": "person",
      "primary": false,
      "person_id": "~{\"name\": \"Murman\"}",
      "organization_id": null
    },
    {
      "name": "Lippincott",
      "classification": "cosponsor",
      "entity_type": "person",
      "primary": false,
      "person_id": "~{\"name\": \"Lippincott\"}",
      "organization_id": null
    },
    {
      "name": "Andersen",
      "classification": "cosponsor",
      "entity_type": "person",
      "primary": false,
      "person_id": "~{\"name\": \"Andersen\"}",
      "organization_id": null
    },
    {
      "name": "Hardin",
      "classification": "cosponsor",
      "entity_type": "person",
      "primary": false,
      "person_id": "~{\"name\": \"Hardin\"}",
      "organization_id": null
    },
    {
      "name": "Cavanaugh, J.",
      "classification": "cosponsor",
      "entity_type": "person",
      "primary": false,
      "person_id": "~{\"name\": \"Cavanaugh, J.\"}",
      "organization_id": null
    },
    {
      "name": "Dover",
      "classification": "cosponsor",
      "entity_type": "person",
      "primary": false,
      "person_id": "~{\"name\": \"Dover\"}",
      "organization_id": null
    },
    {
      "name": "Bostar",
      "classification": "cosponsor",
      "entity_type": "person",
      "primary": false,
      "person_id": "~{\"name\": \"Bostar\"}",
      "organization_id": null
    },
    {
      "name": "Conrad",
      "classification": "cosponsor",
      "entity_type": "person",
      "primary": false,
      "person_id": "~{\"name\": \"Conrad\"}",
      "organization_id": null
    }
  ],
  "related_bills": [],
  "versions": [
    {
      "note": "Introduced",
      "links": [
        {
          "url": "https://nebraskalegislature.gov/FloorDocs/109/PDF/Intro/LB938.pdf",
          "media_type": "application/pdf"
        }
      ],
      "date": "",
      "classification": ""
    }
  ],
  "documents": [
    {
      "note": "Statement of Intent",
      "links": [
        {
          "url": "https://nebraskalegislature.gov/FloorDocs/109/PDF/SI/LB938.pdf",
          "media_type": "application/pdf"
        }
      ],
      "date": "",
      "classification": ""
    },
    {
      "note": "Committee Statement",
      "links": [
        {
          "url": "https://nebraskalegislature.gov/FloorDocs/109/PDF/CS/LB938.pdf",
          "media_type": "application/pdf"
        }
      ],
      "date": "",
      "classification": ""
    },
    {
      "note": "Fiscal Note",
      "links": [
        {
          "url": "https://nebraskalegislature.gov/bills/view_fiscal.php?DocumentID=63361",
          "media_type": "application/pdf"
        }
      ],
      "date": "",
      "classification": ""
    }
  ],
  "citations": [],
  "sources": [
    {
      "url": "https://nebraskalegislature.gov/bills/search_by_date.php?SessionDay=2026",
      "note": ""
    },
    {
      "url": "https://nebraskalegislature.gov/bills/view_bill.php?DocumentID=63361",
      "note": ""
    }
  ],
  "extras": {
    "NE_REF_DATE": "February 12, 2026",
    "NE_REF_COM": "Revenue Committee",
    "NE_PRIORITIZER": "Senator Storm"
  },
  "jurisdiction": {
    "id": "ocd-jurisdiction/country:us/state:ne/government",
    "name": "Nebraska",
    "classification": "state",
    "division_id": "ocd-division/country:us/state:ne"
  },
  "_processing": {
    "logs_latest_update": "2026-07-14T13:00:28Z"
  }
}