{
  "legislative_session": "109",
  "identifier": "LB877",
  "title": "Designate certain substances as controlled substances under the Uniform Controlled Substances Act",
  "from_organization": "~{\"classification\": \"legislature\"}",
  "classification": [
    "bill"
  ],
  "subject": [],
  "abstracts": [],
  "other_titles": [],
  "other_identifiers": [
    {
      "identifier": "ocd-bill-ne-109-lb877"
    }
  ],
  "actions": [
    {
      "description": "Approved by Governor on March 3, 2026",
      "date": "2026-03-03",
      "organization_id": "~{\"classification\": \"executive\"}",
      "classification": [
        "executive-signature"
      ],
      "related_entities": [],
      "_processing": {
        "log_file_created": "2026-07-14T13:00:27Z"
      }
    },
    {
      "description": "Presented to Governor on  February 27, 2026",
      "date": "2026-03-03",
      "organization_id": "~{\"classification\": \"executive\"}",
      "classification": [
        "executive-receipt"
      ],
      "related_entities": [],
      "_processing": {
        "log_file_created": "2026-07-14T13:00:27Z"
      }
    },
    {
      "description": "President/Speaker signed",
      "date": "2026-02-27",
      "organization_id": "~{\"classification\": \"legislature\"}",
      "classification": [
        "passage"
      ],
      "related_entities": [],
      "_processing": {
        "log_file_created": "2026-07-14T13:00:27Z"
      }
    },
    {
      "description": "Passed on Final Reading 42-6*-1",
      "date": "2026-02-27",
      "organization_id": "~{\"classification\": \"legislature\"}",
      "classification": [
        "passage"
      ],
      "related_entities": [],
      "_processing": {
        "log_file_created": "2026-07-14T13:00:27Z"
      }
    },
    {
      "description": "Dispensing of reading at large approved",
      "date": "2026-02-27",
      "organization_id": "~{\"classification\": \"legislature\"}",
      "classification": [],
      "related_entities": [],
      "_processing": {
        "log_file_created": "2026-07-14T13:00:27Z"
      }
    },
    {
      "description": "Conrad FA984 withdrawn",
      "date": "2026-02-27",
      "organization_id": "~{\"classification\": \"legislature\"}",
      "classification": [],
      "related_entities": [],
      "_processing": {
        "log_file_created": "2026-07-14T13:00:27Z"
      }
    },
    {
      "description": "Conrad FA983 withdrawn",
      "date": "2026-02-27",
      "organization_id": "~{\"classification\": \"legislature\"}",
      "classification": [],
      "related_entities": [],
      "_processing": {
        "log_file_created": "2026-07-14T13:00:27Z"
      }
    },
    {
      "description": "Conrad MO424 withdrawn",
      "date": "2026-02-27",
      "organization_id": "~{\"classification\": \"legislature\"}",
      "classification": [],
      "related_entities": [],
      "_processing": {
        "log_file_created": "2026-07-14T13:00:27Z"
      }
    },
    {
      "description": "Placed on Final Reading",
      "date": "2026-02-24",
      "organization_id": "~{\"classification\": \"legislature\"}",
      "classification": [
        "reading-3"
      ],
      "related_entities": [],
      "_processing": {
        "log_file_created": "2026-07-14T13:00:27Z"
      }
    },
    {
      "description": "Advanced to Enrollment and Review for Engrossment",
      "date": "2026-02-19",
      "organization_id": "~{\"classification\": \"legislature\"}",
      "classification": [],
      "related_entities": [],
      "_processing": {
        "log_file_created": "2026-07-14T13:00:27Z"
      }
    },
    {
      "description": "Kauth FA517 withdrawn",
      "date": "2026-02-19",
      "organization_id": "~{\"classification\": \"legislature\"}",
      "classification": [],
      "related_entities": [],
      "_processing": {
        "log_file_created": "2026-07-14T13:00:27Z"
      }
    },
    {
      "description": "Conrad FA976 withdrawn",
      "date": "2026-02-19",
      "organization_id": "~{\"classification\": \"legislature\"}",
      "classification": [],
      "related_entities": [],
      "_processing": {
        "log_file_created": "2026-07-14T13:00:27Z"
      }
    },
    {
      "description": "Conrad FA975 withdrawn",
      "date": "2026-02-19",
      "organization_id": "~{\"classification\": \"legislature\"}",
      "classification": [],
      "related_entities": [],
      "_processing": {
        "log_file_created": "2026-07-14T13:00:27Z"
      }
    },
    {
      "description": "Conrad MO418 withdrawn",
      "date": "2026-02-19",
      "organization_id": "~{\"classification\": \"legislature\"}",
      "classification": [],
      "related_entities": [],
      "_processing": {
        "log_file_created": "2026-07-14T13:00:27Z"
      }
    },
    {
      "description": "Conrad MO417 withdrawn",
      "date": "2026-02-19",
      "organization_id": "~{\"classification\": \"legislature\"}",
      "classification": [],
      "related_entities": [],
      "_processing": {
        "log_file_created": "2026-07-14T13:00:27Z"
      }
    },
    {
      "description": "Conrad MO416 withdrawn",
      "date": "2026-02-19",
      "organization_id": "~{\"classification\": \"legislature\"}",
      "classification": [],
      "related_entities": [],
      "_processing": {
        "log_file_created": "2026-07-14T13:00:27Z"
      }
    },
    {
      "description": "Enrollment and Review ER117 adopted",
      "date": "2026-02-19",
      "organization_id": "~{\"classification\": \"legislature\"}",
      "classification": [],
      "related_entities": [],
      "_processing": {
        "log_file_created": "2026-07-14T13:00:27Z"
      }
    },
    {
      "description": "Conrad FA984 filed",
      "date": "2026-02-18",
      "organization_id": "~{\"classification\": \"legislature\"}",
      "classification": [
        "filing"
      ],
      "related_entities": [],
      "_processing": {
        "log_file_created": "2026-07-14T13:00:27Z"
      }
    },
    {
      "description": "Conrad FA983 filed",
      "date": "2026-02-18",
      "organization_id": "~{\"classification\": \"legislature\"}",
      "classification": [
        "filing"
      ],
      "related_entities": [],
      "_processing": {
        "log_file_created": "2026-07-14T13:00:27Z"
      }
    },
    {
      "description": "Conrad MO424 Recommit to the Judiciary Committee filed",
      "date": "2026-02-18",
      "organization_id": "~{\"classification\": \"legislature\"}",
      "classification": [
        "filing"
      ],
      "related_entities": [],
      "_processing": {
        "log_file_created": "2026-07-14T13:00:27Z"
      }
    },
    {
      "description": "Conrad MO418 Indefinitely postpone filed",
      "date": "2026-02-17",
      "organization_id": "~{\"classification\": \"legislature\"}",
      "classification": [
        "filing"
      ],
      "related_entities": [],
      "_processing": {
        "log_file_created": "2026-07-14T13:00:27Z"
      }
    },
    {
      "description": "Conrad MO417 Recommit to the Judiciary Committee filed",
      "date": "2026-02-17",
      "organization_id": "~{\"classification\": \"legislature\"}",
      "classification": [
        "filing"
      ],
      "related_entities": [],
      "_processing": {
        "log_file_created": "2026-07-14T13:00:27Z"
      }
    },
    {
      "description": "Conrad MO416 Bracket until April 17, 2026 filed",
      "date": "2026-02-17",
      "organization_id": "~{\"classification\": \"legislature\"}",
      "classification": [
        "filing"
      ],
      "related_entities": [],
      "_processing": {
        "log_file_created": "2026-07-14T13:00:27Z"
      }
    },
    {
      "description": "Conrad FA976 filed",
      "date": "2026-02-17",
      "organization_id": "~{\"classification\": \"legislature\"}",
      "classification": [
        "filing"
      ],
      "related_entities": [],
      "_processing": {
        "log_file_created": "2026-07-14T13:00:27Z"
      }
    },
    {
      "description": "Conrad FA975 filed",
      "date": "2026-02-17",
      "organization_id": "~{\"classification\": \"legislature\"}",
      "classification": [
        "filing"
      ],
      "related_entities": [],
      "_processing": {
        "log_file_created": "2026-07-14T13:00:27Z"
      }
    },
    {
      "description": "Enrollment and Review ER117 filed",
      "date": "2026-02-10",
      "organization_id": "~{\"classification\": \"legislature\"}",
      "classification": [
        "filing"
      ],
      "related_entities": [],
      "_processing": {
        "log_file_created": "2026-07-14T13:00:27Z"
      }
    },
    {
      "description": "Placed on Select File with ER117",
      "date": "2026-02-10",
      "organization_id": "~{\"classification\": \"legislature\"}",
      "classification": [
        "filing"
      ],
      "related_entities": [],
      "_processing": {
        "log_file_created": "2026-07-14T13:00:27Z"
      }
    },
    {
      "description": "Advanced to Enrollment and Review Initial",
      "date": "2026-02-04",
      "organization_id": "~{\"classification\": \"legislature\"}",
      "classification": [],
      "related_entities": [],
      "_processing": {
        "log_file_created": "2026-07-14T13:00:27Z"
      }
    },
    {
      "description": "DeKay AM1818 withdrawn",
      "date": "2026-02-04",
      "organization_id": "~{\"classification\": \"legislature\"}",
      "classification": [],
      "related_entities": [],
      "_processing": {
        "log_file_created": "2026-07-14T13:00:27Z"
      }
    },
    {
      "description": "Judiciary AM1763 adopted",
      "date": "2026-02-04",
      "organization_id": "~{\"classification\": \"legislature\"}",
      "classification": [],
      "related_entities": [],
      "_processing": {
        "log_file_created": "2026-07-14T13:00:27Z"
      }
    },
    {
      "description": "Judiciary AM1763 filed",
      "date": "2026-01-29",
      "organization_id": "~{\"classification\": \"legislature\"}",
      "classification": [
        "filing"
      ],
      "related_entities": [],
      "_processing": {
        "log_file_created": "2026-07-14T13:00:27Z"
      }
    },
    {
      "description": "Placed on General File with AM1763",
      "date": "2026-01-29",
      "organization_id": "~{\"classification\": \"legislature\"}",
      "classification": [
        "committee-passage"
      ],
      "related_entities": [],
      "_processing": {
        "log_file_created": "2026-07-14T13:00:27Z"
      }
    },
    {
      "description": "DeKay AM1818 filed",
      "date": "2026-01-28",
      "organization_id": "~{\"classification\": \"legislature\"}",
      "classification": [
        "filing"
      ],
      "related_entities": [],
      "_processing": {
        "log_file_created": "2026-07-14T13:00:27Z"
      }
    },
    {
      "description": "Notice of hearing for January 22, 2026",
      "date": "2026-01-14",
      "organization_id": "~{\"classification\": \"legislature\"}",
      "classification": [],
      "related_entities": [],
      "_processing": {
        "log_file_created": "2026-07-14T13:00:27Z"
      }
    },
    {
      "description": "Referred to Judiciary Committee",
      "date": "2026-01-12",
      "organization_id": "~{\"classification\": \"legislature\"}",
      "classification": [
        "referral-committee"
      ],
      "related_entities": [],
      "_processing": {
        "log_file_created": "2026-07-14T13:00:27Z"
      }
    },
    {
      "description": "Kauth FA517 filed",
      "date": "2026-01-09",
      "organization_id": "~{\"classification\": \"legislature\"}",
      "classification": [
        "filing"
      ],
      "related_entities": [],
      "_processing": {
        "log_file_created": "2026-07-14T13:00:27Z"
      }
    },
    {
      "description": "Date of introduction",
      "date": "2026-01-08",
      "organization_id": "~{\"classification\": \"legislature\"}",
      "classification": [
        "introduction"
      ],
      "related_entities": [],
      "_processing": {
        "log_file_created": "2026-07-14T13:00:27Z"
      }
    }
  ],
  "sponsorships": [
    {
      "name": "Hallstrom",
      "classification": "primary",
      "entity_type": "person",
      "primary": true,
      "person_id": "~{\"name\": \"Hallstrom\"}",
      "organization_id": null
    }
  ],
  "related_bills": [],
  "versions": [
    {
      "note": "Introduced",
      "links": [
        {
          "url": "https://nebraskalegislature.gov/FloorDocs/109/PDF/Intro/LB877.pdf",
          "media_type": "application/pdf"
        }
      ],
      "date": "",
      "classification": ""
    },
    {
      "note": "Final Reading",
      "links": [
        {
          "url": "https://nebraskalegislature.gov/FloorDocs/109/PDF/Final/LB877.pdf",
          "media_type": "application/pdf"
        }
      ],
      "date": "",
      "classification": ""
    },
    {
      "note": "Slip Law",
      "links": [
        {
          "url": "https://nebraskalegislature.gov/FloorDocs/109/PDF/Slip/LB877.pdf",
          "media_type": "application/pdf"
        }
      ],
      "date": "",
      "classification": ""
    },
    {
      "note": "Judiciary AM1763",
      "links": [
        {
          "url": "https://nebraskalegislature.gov/FloorDocs/109/PDF/AM/AM1763.pdf",
          "media_type": "application/pdf"
        }
      ],
      "date": "",
      "classification": ""
    },
    {
      "note": "Enrollment and Review ER117",
      "links": [
        {
          "url": "https://nebraskalegislature.gov/FloorDocs/109/PDF/AM/ER117.pdf",
          "media_type": "application/pdf"
        }
      ],
      "date": "",
      "classification": ""
    }
  ],
  "documents": [
    {
      "note": "Statement of Intent",
      "links": [
        {
          "url": "https://nebraskalegislature.gov/FloorDocs/109/PDF/SI/LB877.pdf",
          "media_type": "application/pdf"
        }
      ],
      "date": "",
      "classification": ""
    },
    {
      "note": "Committee Statement",
      "links": [
        {
          "url": "https://nebraskalegislature.gov/FloorDocs/109/PDF/CS/LB877.pdf",
          "media_type": "application/pdf"
        }
      ],
      "date": "",
      "classification": ""
    },
    {
      "note": "Fiscal Note",
      "links": [
        {
          "url": "https://nebraskalegislature.gov/bills/view_fiscal.php?DocumentID=63292",
          "media_type": "application/pdf"
        }
      ],
      "date": "",
      "classification": ""
    },
    {
      "note": "DeKay AM1818 (withdrawn)",
      "links": [
        {
          "url": "https://nebraskalegislature.gov/FloorDocs/109/PDF/AM/AM1818.pdf",
          "media_type": "application/pdf"
        }
      ],
      "date": "",
      "classification": ""
    },
    {
      "note": "Conrad MO416 (withdrawn)",
      "links": [
        {
          "url": "https://nebraskalegislature.gov/FloorDocs/109/PDF/AM/MO416.pdf",
          "media_type": "application/pdf"
        }
      ],
      "date": "",
      "classification": ""
    },
    {
      "note": "Conrad MO417 (withdrawn)",
      "links": [
        {
          "url": "https://nebraskalegislature.gov/FloorDocs/109/PDF/AM/MO417.pdf",
          "media_type": "application/pdf"
        }
      ],
      "date": "",
      "classification": ""
    },
    {
      "note": "Conrad MO418 (withdrawn)",
      "links": [
        {
          "url": "https://nebraskalegislature.gov/FloorDocs/109/PDF/AM/MO418.pdf",
          "media_type": "application/pdf"
        }
      ],
      "date": "",
      "classification": ""
    },
    {
      "note": "Conrad FA975 (withdrawn)",
      "links": [
        {
          "url": "https://nebraskalegislature.gov/FloorDocs/109/PDF/AM/FA975.pdf",
          "media_type": "application/pdf"
        }
      ],
      "date": "",
      "classification": ""
    },
    {
      "note": "Conrad FA976 (withdrawn)",
      "links": [
        {
          "url": "https://nebraskalegislature.gov/FloorDocs/109/PDF/AM/FA976.pdf",
          "media_type": "application/pdf"
        }
      ],
      "date": "",
      "classification": ""
    },
    {
      "note": "Kauth FA517 (withdrawn)",
      "links": [
        {
          "url": "https://nebraskalegislature.gov/FloorDocs/109/PDF/AM/FA517.pdf",
          "media_type": "application/pdf"
        }
      ],
      "date": "",
      "classification": ""
    },
    {
      "note": "Conrad MO424 (withdrawn)",
      "links": [
        {
          "url": "https://nebraskalegislature.gov/FloorDocs/109/PDF/AM/MO424.pdf",
          "media_type": "application/pdf"
        }
      ],
      "date": "",
      "classification": ""
    },
    {
      "note": "Conrad FA983 (withdrawn)",
      "links": [
        {
          "url": "https://nebraskalegislature.gov/FloorDocs/109/PDF/AM/FA983.pdf",
          "media_type": "application/pdf"
        }
      ],
      "date": "",
      "classification": ""
    },
    {
      "note": "Conrad FA984 (withdrawn)",
      "links": [
        {
          "url": "https://nebraskalegislature.gov/FloorDocs/109/PDF/AM/FA984.pdf",
          "media_type": "application/pdf"
        }
      ],
      "date": "",
      "classification": ""
    }
  ],
  "citations": [],
  "sources": [
    {
      "url": "https://nebraskalegislature.gov/bills/search_by_date.php?SessionDay=2026",
      "note": ""
    },
    {
      "url": "https://nebraskalegislature.gov/bills/view_bill.php?DocumentID=63292",
      "note": ""
    }
  ],
  "extras": {
    "NE_REF_DATE": "January 22, 2026",
    "NE_REF_COM": "Judiciary Committee"
  },
  "jurisdiction": {
    "id": "ocd-jurisdiction/country:us/state:ne/government",
    "name": "Nebraska",
    "classification": "state",
    "division_id": "ocd-division/country:us/state:ne"
  },
  "_processing": {
    "logs_latest_update": "2026-07-14T13:00:27Z"
  }
}